waveboxgen/__init__.py
waveboxgen/main.py
waveboxgen/templates/__init__.py
waveboxgen/utils/__init__.py
waveboxgen/utils/converter.py
waveboxgen-0.0.3.dist-info/LICENSE
waveboxgen-0.0.3.dist-info/METADATA
waveboxgen-0.0.3.dist-info/WHEEL
waveboxgen-0.0.3.dist-info/entry_points.txt
waveboxgen-0.0.3.dist-info/top_level.txt
waveboxgen-0.0.3.dist-info/RECORD
