Metadata-Version: 2.1
Name: waveboxgen
Version: 0.0.3
Summary: A Wavebox framework file generator
Author-email: Oktaviano Fahdi Syaputra <adorufus@gmail.com>
Project-URL: Homepage, https://github.com/adorufus/waveboxgen
Project-URL: Bug Tracker, https://github.com/adorufus/waveboxgen/issues
Classifier: Programming Language :: Python :: 3
Classifier: License :: OSI Approved :: MIT License
Classifier: Operating System :: OS Independent
Requires-Python: >=3.10
License-File: LICENSE
